{
  "players": [
    "Akash",
    "Aman",
    "Gagan",
    "Robby",
    "Matab",
    "Dilaver",
    "Pardeep",
    "Harjit",
    "Harman",
    "Randy",
    "Surkh",
    "Hinda",
    "Jodha",
    "Goldy"
  ],
  "nicknames": {},
  "bets": {
    "Robby": {
      "0": {
        "pick": "Hinda",
        "amount": 20
      },
      "1": {
        "pick": "Harman",
        "amount": 50
      },
      "2": {
        "pick": "Aman",
        "amount": 5
      },
      "3": {
        "pick": "Harman",
        "amount": 5
      },
      "4": {
        "pick": "Randy",
        "amount": 5
      },
      "5": {
        "pick": "Jodha",
        "amount": 5
      },
      "6": {
        "pick": "Aman",
        "amount": 5
      },
      "7": {
        "pick": "Matab",
        "amount": 5
      },
      "8": {
        "pick": "Harman",
        "amount": 5
      },
      "9": {
        "pick": "Hinda",
        "amount": 5
      },
      "10": {
        "pick": "Jodha",
        "amount": 5
      },
      "11": {
        "pick": "Dilaver",
        "amount": 5
      },
      "12": {
        "pick": "Dilaver",
        "amount": 5
      },
      "13": {
        "pick": "Harman",
        "amount": 5
      },
      "14": {
        "pick": "Matab",
        "amount": 5
      },
      "15": {
        "pick": "Harman",
        "amount": 5
      },
      "16": {
        "pick": "Goldy",
        "amount": 40
      },
      "17": {
        "pick": "Robby",
        "amount": 5
      },
      "18": {
        "pick": "Harman",
        "amount": 5
      },
      "19": {
        "pick": "Gagan",
        "amount": 5
      },
      "20": {
        "pick": "Akash",
        "amount": 5
      },
      "21": {
        "pick": "Harman",
        "amount": 5
      },
      "22": {
        "pick": "Robby",
        "amount": 5
      },
      "23": {
        "pick": "Matab",
        "amount": 5
      },
      "24": {
        "pick": "Aman",
        "amount": 5
      },
      "25": {
        "pick": "Hinda",
        "amount": 30
      }
    },
    "Matab": {
      "0": {
        "pick": "Aman",
        "amount": 5
      },
      "1": {
        "pick": "Harman",
        "amount": 15
      },
      "2": {
        "pick": "Harjit",
        "amount": 10
      },
      "3": {
        "pick": "Robby",
        "amount": 10
      },
      "4": {
        "pick": "Randy",
        "amount": 10
      },
      "5": {
        "pick": "Gagan",
        "amount": 5
      },
      "6": {
        "pick": "Goldy",
        "amount": 10
      },
      "7": {
        "pick": "Dilaver",
        "amount": 5
      },
      "8": {
        "pick": "Harman",
        "amount": 15
      },
      "9": {
        "pick": "Hinda",
        "amount": 10
      },
      "10": {
        "pick": "Harman",
        "amount": 25
      },
      "11": {
        "pick": "Matab",
        "amount": 5
      },
      "12": {
        "pick": "Surkh",
        "amount": 5
      },
      "13": {
        "pick": "Randy",
        "amount": 10
      },
      "14": {
        "pick": "Akash",
        "amount": 25
      },
      "15": {
        "pick": "Surkh",
        "amount": 5
      },
      "16": {
        "pick": "Matab",
        "amount": 5
      },
      "17": {
        "pick": "Harjit",
        "amount": 5
      },
      "18": {
        "pick": "Randy",
        "amount": 5
      },
      "19": {
        "pick": "Goldy",
        "amount": 5
      },
      "20": {
        "pick": "Robby",
        "amount": 10
      },
      "21": {
        "pick": "Randy",
        "amount": 15
      },
      "22": {
        "pick": "Harman",
        "amount": 5
      },
      "23": {
        "pick": "Pardeep",
        "amount": 5
      },
      "24": {
        "pick": "Harman",
        "amount": 5
      },
      "25": {
        "pick": "Jodha",
        "amount": 20
      }
    },
    "Aman": {
      "0": {
        "pick": "Robby",
        "amount": 15
      },
      "1": {
        "pick": "Surkh",
        "amount": 15
      },
      "2": {
        "pick": "Harman",
        "amount": 10
      },
      "3": {
        "pick": "Robby",
        "amount": 5
      },
      "4": {
        "pick": "Aman",
        "amount": 20
      },
      "5": {
        "pick": "Harjit",
        "amount": 15
      },
      "6": {
        "pick": "Harman",
        "amount": 15
      },
      "7": {
        "pick": "Matab",
        "amount": 5
      },
      "8": {
        "pick": "Harman",
        "amount": 10
      },
      "9": {
        "pick": "Randy",
        "amount": 5
      },
      "10": {
        "pick": "Gagan",
        "amount": 10
      },
      "11": {
        "pick": "Dilaver",
        "amount": 5
      },
      "12": {
        "pick": "Surkh",
        "amount": 15
      },
      "13": {
        "pick": "Harman",
        "amount": 15
      },
      "14": {
        "pick": "Akash",
        "amount": 5
      },
      "15": {
        "pick": "Goldy",
        "amount": 5
      },
      "16": {
        "pick": "Pardeep",
        "amount": 10
      },
      "17": {
        "pick": "Harman",
        "amount": 5
      },
      "18": {
        "pick": "Randy",
        "amount": 15
      },
      "19": {
        "pick": "Robby",
        "amount": 5
      },
      "20": {
        "pick": "Aman",
        "amount": 5
      },
      "21": {
        "pick": "Randy",
        "amount": 20
      },
      "22": {
        "pick": "Matab",
        "amount": 5
      },
      "23": {
        "pick": "Randy",
        "amount": 5
      },
      "24": {
        "pick": "Jodha",
        "amount": 5
      },
      "25": {
        "pick": "Hinda",
        "amount": 5
      }
    },
    "Goldy": {
      "0": {
        "pick": "Randy",
        "amount": 5
      },
      "1": {
        "pick": "Matab",
        "amount": 5
      },
      "2": {
        "pick": "Harman",
        "amount": 5
      },
      "3": {
        "pick": "Aman",
        "amount": 5
      },
      "4": {
        "pick": "Gagan",
        "amount": 10
      },
      "5": {
        "pick": "Pardeep",
        "amount": 5
      },
      "6": {
        "pick": "Hinda",
        "amount": 5
      },
      "7": {
        "pick": "Akash",
        "amount": 5
      },
      "8": {
        "pick": "Harman",
        "amount": 15
      },
      "9": {
        "pick": "Hinda",
        "amount": 5
      },
      "10": {
        "pick": "Aman",
        "amount": 10
      },
      "11": {
        "pick": "Gagan",
        "amount": 5
      },
      "12": {
        "pick": "Matab",
        "amount": 5
      },
      "13": {
        "pick": "Goldy",
        "amount": 5
      },
      "14": {
        "pick": "Akash",
        "amount": 10
      },
      "15": {
        "pick": "Randy",
        "amount": 5
      },
      "16": {
        "pick": "Randy",
        "amount": 20
      },
      "17": {
        "pick": "Harman",
        "amount": 15
      },
      "18": {
        "pick": "Goldy",
        "amount": 5
      },
      "19": {
        "pick": "Matab",
        "amount": 5
      },
      "20": {
        "pick": "Robby",
        "amount": 5
      },
      "21": {
        "pick": "Matab",
        "amount": 5
      },
      "22": {
        "pick": "Akash",
        "amount": 5
      },
      "23": {
        "pick": "Jodha",
        "amount": 5
      },
      "24": {
        "pick": "Harjit",
        "amount": 15
      },
      "25": {
        "pick": "Hinda",
        "amount": 5
      }
    },
    "Akash": {
      "0": {
        "pick": "Robby",
        "amount": 5
      },
      "1": {
        "pick": "Harman",
        "amount": 5
      },
      "2": {
        "pick": "Harjit",
        "amount": 5
      },
      "3": {
        "pick": "Robby",
        "amount": 5
      },
      "4": {
        "pick": "Akash",
        "amount": 5
      },
      "5": {
        "pick": "Gagan",
        "amount": 5
      },
      "6": {
        "pick": "Goldy",
        "amount": 5
      },
      "7": {
        "pick": "Akash",
        "amount": 10
      },
      "8": {
        "pick": "Harman",
        "amount": 5
      },
      "9": {
        "pick": "Hinda",
        "amount": 5
      },
      "10": {
        "pick": "Gagan",
        "amount": 25
      },
      "11": {
        "pick": "Aman",
        "amount": 5
      },
      "12": {
        "pick": "Surkh",
        "amount": 5
      },
      "13": {
        "pick": "Randy",
        "amount": 5
      },
      "14": {
        "pick": "Akash",
        "amount": 5
      },
      "15": {
        "pick": "Surkh",
        "amount": 5
      },
      "16": {
        "pick": "Dilaver",
        "amount": 5
      },
      "17": {
        "pick": "Harjit",
        "amount": 5
      },
      "18": {
        "pick": "Randy",
        "amount": 5
      },
      "19": {
        "pick": "Gagan",
        "amount": 5
      },
      "20": {
        "pick": "Robby",
        "amount": 5
      },
      "21": {
        "pick": "Randy",
        "amount": 5
      },
      "22": {
        "pick": "Robby",
        "amount": 5
      },
      "23": {
        "pick": "Matab",
        "amount": 5
      },
      "24": {
        "pick": "Harman",
        "amount": 5
      },
      "25": {
        "pick": "Hinda",
        "amount": 5
      }
    },
    "Dilaver": {
      "0": {
        "pick": "Randy",
        "amount": 5
      },
      "1": {
        "pick": "Harjit",
        "amount": 10
      },
      "2": {
        "pick": "Harman",
        "amount": 25
      },
      "3": {
        "pick": "Harjit",
        "amount": 5
      },
      "4": {
        "pick": "Aman",
        "amount": 15
      },
      "5": {
        "pick": "Gagan",
        "amount": 10
      },
      "6": {
        "pick": "Harman",
        "amount": 15
      },
      "7": {
        "pick": "Harman",
        "amount": 5
      },
      "8": {
        "pick": "Harman",
        "amount": 15
      },
      "9": {
        "pick": "Hinda",
        "amount": 20
      },
      "10": {
        "pick": "Harman",
        "amount": 10
      },
      "11": {
        "pick": "Goldy",
        "amount": 20
      },
      "12": {
        "pick": "Surkh",
        "amount": 10
      },
      "13": {
        "pick": "Harman",
        "amount": 15
      },
      "14": {
        "pick": "Akash",
        "amount": 15
      },
      "15": {
        "pick": "Matab",
        "amount": 5
      },
      "16": {
        "pick": "Matab",
        "amount": 5
      },
      "17": {
        "pick": "Harman",
        "amount": 5
      },
      "18": {
        "pick": "Randy",
        "amount": 5
      },
      "19": {
        "pick": "Harman",
        "amount": 5
      },
      "20": {
        "pick": "Randy",
        "amount": 5
      },
      "21": {
        "pick": "Matab",
        "amount": 5
      },
      "22": {
        "pick": "Aman",
        "amount": 5
      },
      "23": {
        "pick": "Harman",
        "amount": 5
      },
      "24": {
        "pick": "Hinda",
        "amount": 5
      },
      "25": {
        "pick": "Surkh",
        "amount": 5
      }
    },
    "Gagan": {
      "0": {
        "pick": "Robby",
        "amount": 10
      },
      "1": {
        "pick": "Harman",
        "amount": 15
      },
      "2": {
        "pick": "Harman",
        "amount": 20
      },
      "3": {
        "pick": "Harjit",
        "amount": 5
      },
      "4": {
        "pick": "Aman",
        "amount": 10
      },
      "5": {
        "pick": "Pardeep",
        "amount": 10
      },
      "6": {
        "pick": "Matab",
        "amount": 10
      },
      "7": {
        "pick": "Akash",
        "amount": 10
      },
      "8": {
        "pick": "Harman",
        "amount": 15
      },
      "9": {
        "pick": "Jodha",
        "amount": 5
      },
      "10": {
        "pick": "Harman",
        "amount": 10
      },
      "11": {
        "pick": "Gagan",
        "amount": 5
      },
      "12": {
        "pick": "Surkh",
        "amount": 15
      },
      "13": {
        "pick": "Harjit",
        "amount": 10
      },
      "14": {
        "pick": "Matab",
        "amount": 5
      },
      "15": {
        "pick": "Randy",
        "amount": 5
      },
      "16": {
        "pick": "Akash",
        "amount": 5
      },
      "17": {
        "pick": "Harjit",
        "amount": 10
      },
      "18": {
        "pick": "Randy",
        "amount": 15
      },
      "19": {
        "pick": "Gagan",
        "amount": 10
      },
      "20": {
        "pick": "Matab",
        "amount": 10
      },
      "21": {
        "pick": "Randy",
        "amount": 15
      },
      "22": {
        "pick": "Robby",
        "amount": 5
      },
      "23": {
        "pick": "Matab",
        "amount": 5
      },
      "24": {
        "pick": "Aman",
        "amount": 5
      },
      "25": {
        "pick": "Hinda",
        "amount": 10
      }
    },
    "Hinda": {
      "0": {
        "pick": "Robby",
        "amount": 5
      },
      "1": {
        "pick": "Harman",
        "amount": 20
      },
      "2": {
        "pick": "Aman",
        "amount": 5
      },
      "3": {
        "pick": "Harjit",
        "amount": 10
      },
      "4": {
        "pick": "Akash",
        "amount": 5
      },
      "5": {
        "pick": "Aman",
        "amount": 5
      },
      "6": {
        "pick": "Aman",
        "amount": 5
      },
      "7": {
        "pick": "Matab",
        "amount": 5
      },
      "8": {
        "pick": "Hinda",
        "amount": 5
      },
      "9": {
        "pick": "Hinda",
        "amount": 5
      },
      "10": {
        "pick": "Harman",
        "amount": 5
      },
      "11": {
        "pick": "Goldy",
        "amount": 5
      },
      "12": {
        "pick": "Dilaver",
        "amount": 5
      },
      "13": {
        "pick": "Harman",
        "amount": 25
      },
      "14": {
        "pick": "Aman",
        "amount": 10
      },
      "15": {
        "pick": "Randy",
        "amount": 5
      },
      "16": {
        "pick": "Harman",
        "amount": 10
      },
      "17": {
        "pick": "Harman",
        "amount": 25
      },
      "18": {
        "pick": "Harman",
        "amount": 25
      },
      "20": {
        "pick": "Randy",
        "amount": 15
      },
      "21": {
        "pick": "Randy",
        "amount": 25
      },
      "22": {
        "pick": "Harman",
        "amount": 10
      },
      "23": {
        "pick": "Harman",
        "amount": 10
      }
    },
    "Harjit": {
      "0": {
        "pick": "Matab",
        "amount": 25
      },
      "5": {
        "pick": "Goldy",
        "amount": 5
      },
      "6": {
        "pick": "Harman",
        "amount": 15
      }
    }
  },
  "lockedPlayers": [
    "Matab",
    "Robby",
    "Dilaver",
    "Gagan"
  ],
  "resolutions": {},
  "favoriteOverrides": {},
  "playerPasswords": {
    "Akash": "Rav",
    "Robby": "muxJuw-wyrxop-jybxi5",
    "Matab": "Branvan2000",
    "Aman": "Potter28",
    "Gagan": "Potter10!",
    "Jodha": "pussypie",
    "Goldy": "fetmah-3quwwo-nuhPig",
    "Dilaver": "9055078054",
    "Hinda": "asdasd123",
    "Harjit": "sacrebleu"
  },
  "questions": [
    "Who is most likely to be the first person to complain about the car, the temperature, the drive, or say that you all should have just flown?",
    "Who is most likely to be the reason you're late to literally everything?",
    "Who is most likely to be the first person to become best friends with a stranger?",
    "Who is most likely to be the first person to act as a wingman for someone?",
    "Who is most likely to be the first person to suggest getting shots?",
    "Who is most likely to be the first person to chug a full can of beer?",
    "Who is most likely to be the first person to become too loud at dinner?",
    "Who is most likely to be the first person to record a video with a stranger in it and make the stranger say something in Punjabi?",
    "Who is most likely to get sentimental and cry?",
    "Who is most likely to be the first person to lose their phone or wallet?",
    "Who is most likely to yak on the first night?",
    "Who is most likely to be the first person to wake up on Saturday morning?",
    "Who is most likely to be the first person to fall asleep on Friday night?",
    "Who is most likely to end up on the double bed or sofa bed?",
    "Who is most likely to get the bachelor trip's best group photo?",
    "Who is most likely to get kicked out of a bar?",
    "Who is least likely to take their shirt off?",
    "Who is most likely to be the last person to fall asleep on Friday night?",
    "Who is most likely to disappear for two hours and come back like nothing happened?",
    "Who is most likely to try speaking French and completely butcher it?",
    "Who is most likely to order a huge poutine and not come close to finishing it?",
    "Who is most likely to miss breakfast or lunch on Saturday?",
    "Who is most likely to say \"one more\" 6 times in a row?",
    "Who is most likely to be the last one to leave the bar?",
    "Who is most likely to lose their voice by Saturday afternoon?",
    "Who is most likely to wake up needing a full debrief and still say, \"I wasn't even that drunk\"?"
  ],
  "gamePhase": "setup",
  "config": {
    "totalBudget": 250,
    "minBetPerQuestion": 5,
    "questionCount": 26,
    "maxSelfBets": 3
  },
  "bettingClosed": false
}